crafty_controller_api/__init__.py
crafty_controller_api/api.py
crafty_controller_api-0.1.4.dist-info/LICENSE
crafty_controller_api-0.1.4.dist-info/METADATA
crafty_controller_api-0.1.4.dist-info/WHEEL
crafty_controller_api-0.1.4.dist-info/top_level.txt
crafty_controller_api-0.1.4.dist-info/RECORD
